aell/__init__.py
aell/ael.py
aell/ec/__init__.py
aell/ec/evolution.py
aell/ec/interface_EC.py
aell/ec/management.py
aell/ec/selection.py
aell/llm/__init__.py
aell/llm/api_api2d.py
aell/llm/api_general.py
aell/llm/api_hf_inter.py
aell/llm/interface_LLM.py
aell/utils/__init__.py
aell/utils/createFolders.py
aell/utils/get_algorithm&code.py
aell/utils/get_algorithm&code_pop.py
aell-0.0.1.dist-info/LICENSE
aell-0.0.1.dist-info/METADATA
aell-0.0.1.dist-info/WHEEL
aell-0.0.1.dist-info/top_level.txt
aell-0.0.1.dist-info/RECORD
