Metadata-Version: 2.1
Name: aell
Version: 0.0.1
Summary: Algorithm Evolution using Large Language Model
Author: Fei Liu
Author-email: Fei Liu <fliu36-c@my.cityu.edu.hk>
Project-URL: Homepage, https://github.com/FeiLiu36/AEL
Classifier: Programming Language :: Python :: 3
Classifier: License :: OSI Approved :: MIT License
Classifier: Operating System :: OS Independent
Requires-Python: >=3.8
License-File: LICENSE
